scrapy_proxy_ip_pool/__init__.py
scrapy_proxy_ip_pool/proxy_pool_downloader_middleware.py
scrapy_proxy_ip_pool-1.0.2.dist-info/METADATA
scrapy_proxy_ip_pool-1.0.2.dist-info/WHEEL
scrapy_proxy_ip_pool-1.0.2.dist-info/entry_points.txt
scrapy_proxy_ip_pool-1.0.2.dist-info/top_level.txt
scrapy_proxy_ip_pool-1.0.2.dist-info/RECORD
