Metadata-Version: 2.2
Name: scrapy_proxy_ip_pool
Version: 1.0.2
Summary: 这是一个Scrapy中间件，用于管理代理IP池(支持使用Redis作为代理池)。
Home-page: https://github.com/Tlyer233/Scrapy-Proxy-IP-Pool
Author: 明廷盛
Author-email: 1594365335@qq.com
Classifier: Programming Language :: Python :: 3
Classifier: Framework :: Scrapy
Requires-Dist: Twisted>=20.3.0
Requires-Dist: zope.interface>=5
Requires-Dist: scrapy>=2.12.0
Requires-Dist: redis>=5.2.1
Requires-Dist: loguru>=0.7.2
Dynamic: author
Dynamic: author-email
Dynamic: classifier
Dynamic: description
Dynamic: description-content-type
Dynamic: home-page
Dynamic: requires-dist
Dynamic: summary
